readily/#module1.py#
readily/__init__.py
readily/module1.py
readily/__pycache__/module1.cpython-37.pyc
tests/__init__.py
tests/test_module1.py
readily-0.0.3.dist-info/LICENSE.txt
readily-0.0.3.dist-info/METADATA
readily-0.0.3.dist-info/WHEEL
readily-0.0.3.dist-info/top_level.txt
readily-0.0.3.dist-info/RECORD
